{
  "sources": [
    "Tirra",
    "Noto_Serif_Georgian",
    "Noto_Sans_Lycian",
    "Noto_Sans_Old_Permic"
  ],
  "characters": [
    {
      "letter": "A",
      "source_alphabet": "Noto_Sans_Old_Permic",
      "original_char": "ğ£"
    },
    {
      "letter": "B",
      "source_alphabet": "Tirra",
      "original_char": "M"
    },
    {
      "letter": "C",
      "source_alphabet": "Noto_Sans_Lycian",
      "original_char": "ğŠ‰"
    },
    {
      "letter": "D",
      "source_alphabet": "Noto_Sans_Old_Permic",
      "original_char": "ğ·"
    },
    {
      "letter": "E",
      "source_alphabet": "Noto_Sans_Old_Permic",
      "original_char": "ğ»"
    },
    {
      "letter": "F",
      "source_alphabet": "Noto_Serif_Georgian",
      "original_char": "áƒ "
    },
    {
      "letter": "G",
      "source_alphabet": "Noto_Serif_Georgian",
      "original_char": "áƒ¦"
    },
    {
      "letter": "H",
      "source_alphabet": "Noto_Serif_Georgian",
      "original_char": "áƒ¸"
    },
    {
      "letter": "I",
      "source_alphabet": "Tirra",
      "original_char": "X"
    },
    {
      "letter": "J",
      "source_alphabet": "Noto_Sans_Old_Permic",
      "original_char": "ğ›"
    },
    {
      "letter": "K",
      "source_alphabet": "Noto_Serif_Georgian",
      "original_char": "áƒ¹"
    },
    {
      "letter": "L",
      "source_alphabet": "Noto_Serif_Georgian",
      "original_char": "á‚·"
    },
    {
      "letter": "M",
      "source_alphabet": "Tirra",
      "original_char": "T"
    },
    {
      "letter": "N",
      "source_alphabet": "Noto_Serif_Georgian",
      "original_char": "á‚«"
    },
    {
      "letter": "O",
      "source_alphabet": "Noto_Sans_Lycian",
      "original_char": "ğŠ‰"
    },
    {
      "letter": "P",
      "source_alphabet": "Noto_Sans_Old_Permic",
      "original_char": "ğ¿"
    },
    {
      "letter": "Q",
      "source_alphabet": "Noto_Sans_Old_Permic",
      "original_char": "ğ½"
    },
    {
      "letter": "R",
      "source_alphabet": "Tirra",
      "original_char": "V"
    },
    {
      "letter": "S",
      "source_alphabet": "Noto_Sans_Lycian",
      "original_char": "ğŠ"
    },
    {
      "letter": "T",
      "source_alphabet": "Noto_Sans_Lycian",
      "original_char": "ğŠ"
    },
    {
      "letter": "U",
      "source_alphabet": "Noto_Sans_Lycian",
      "original_char": "ğŠš"
    },
    {
      "letter": "V",
      "source_alphabet": "Noto_Serif_Georgian",
      "original_char": "áƒ¨"
    },
    {
      "letter": "W",
      "source_alphabet": "Tirra",
      "original_char": "G"
    },
    {
      "letter": "X",
      "source_alphabet": "Tirra",
      "original_char": "L"
    },
    {
      "letter": "Y",
      "source_alphabet": "Noto_Sans_Lycian",
      "original_char": "ğŠŠ"
    },
    {
      "letter": "Z",
      "source_alphabet": "Noto_Sans_Lycian",
      "original_char": "ğŠ†"
    }
  ]
}